{"is_source_file": true, "format": "JavaScript", "description": "This file contains logic for generating and managing the layout of a Ludo game board, including cell creation, classification (yard, track, home), safe zones, and styling functions.", "external_files": [], "external_methods": [], "published": ["buildCells", "getCell", "getCellStyle", "tokenStyleFor", "TOKEN_RADIUS"], "classes": [], "methods": [{"name": "buildCells(players)", "description": "Generates the game board layout by creating cells with properties such as type, owner, safe zones, and special positions for players.", "scope": "", "scopeKind": ""}, {"name": "getCell(cells, x, y)", "description": "Retrieves a cell from the cells array based on x and y grid coordinates.", "scope": "", "scopeKind": ""}, {"name": "getCellStyle(cell)", "description": "Returns styling information for a cell based on its type (yard, home, or track).", "scope": "", "scopeKind": ""}, {"name": "tokenStyleFor(token, players, isActive)", "description": "Returns styling information for a token based on its player, ownership, and active status.", "scope": "", "scopeKind": ""}], "calls": ["getCell", "getCellStyle", "tokenStyleFor"], "search-terms": ["ludo layout", "cell classification", "track generation", "yard allocation", "safe zones", "player home cells", "board styling"], "state": 2, "file_id": 16, "knowledge_revision": 35, "git_revision": "", "ctags": [{"_type": "tag", "name": "CELL", "path": "/home/kavia/workspace/code-generation/multiplayer-ludo-game-7791-7800/ludo_frontend/src/game/logic/layout.js", "pattern": "/^const CELL = SIZE \\/ GRID;$/", "language": "JavaScript", "kind": "constant"}, {"_type": "tag", "name": "GRID", "path": "/home/kavia/workspace/code-generation/multiplayer-ludo-game-7791-7800/ludo_frontend/src/game/logic/layout.js", "pattern": "/^const GRID = 15;$/", "language": "JavaScript", "kind": "constant"}, {"_type": "tag", "name": "SIZE", "path": "/home/kavia/workspace/code-generation/multiplayer-ludo-game-7791-7800/ludo_frontend/src/game/logic/layout.js", "pattern": "/^const SIZE = 600;$/", "language": "JavaScript", "kind": "constant"}, {"_type": "tag", "name": "TOKEN_RADIUS", "path": "/home/kavia/workspace/code-generation/multiplayer-ludo-game-7791-7800/ludo_frontend/src/game/logic/layout.js", "pattern": "/^export const TOKEN_RADIUS = CELL * 0.28;$/", "language": "JavaScript", "kind": "constant"}, {"_type": "tag", "name": "buildCells", "path": "/home/kavia/workspace/code-generation/multiplayer-ludo-game-7791-7800/ludo_frontend/src/game/logic/layout.js", "pattern": "/^export function buildCells(players) {$/", "language": "JavaScript", "kind": "function", "signature": "(players)"}, {"_type": "tag", "name": "getCell", "path": "/home/kavia/workspace/code-generation/multiplayer-ludo-game-7791-7800/ludo_frontend/src/game/logic/layout.js", "pattern": "/^export function getCell(cells, x, y) {$/", "language": "JavaScript", "kind": "function", "signature": "(cells, x, y)"}, {"_type": "tag", "name": "getCellStyle", "path": "/home/kavia/workspace/code-generation/multiplayer-ludo-game-7791-7800/ludo_frontend/src/game/logic/layout.js", "pattern": "/^export function getCellStyle(cell) {$/", "language": "JavaScript", "kind": "function", "signature": "(cell)"}, {"_type": "tag", "name": "tokenStyleFor", "path": "/home/kavia/workspace/code-generation/multiplayer-ludo-game-7791-7800/ludo_frontend/src/game/logic/layout.js", "pattern": "/^export function tokenStyleFor(token, players, isActive) {$/", "language": "JavaScript", "kind": "function", "signature": "(token, players, isActive)"}, {"_type": "tag", "name": "x", "path": "/home/kavia/workspace/code-generation/multiplayer-ludo-game-7791-7800/ludo_frontend/src/game/logic/layout.js", "pattern": "/^      const base = { x, y, px, py, size: CELL, kind: 'empty', ownerId: null, safe: false };$/", "language": "JavaScript", "kind": "field", "scope": "buildCells.base", "scopeKind": "class"}], "hash": "920d07ab921652f9404aed05d52bc8ae", "format-version": 4, "code-base-name": "ludo_frontend", "filename": "ludo_frontend/src/game/logic/layout.js", "fields": [{"name": "const base = { x, y, px, py, size: CELL, kind: 'empty', ownerId: null, safe: false };", "scope": "buildCells.base", "scopeKind": "class", "description": "unavailable"}], "revision_history": [{"35": ""}]}